{
  "collaboration_id": "ubuntu_collab_20251014_184518",
  "timestamp": "2025-10-14T18:49:30.072231",
  "participating_agents": [
    "Infrastructure",
    "App Support"
  ],
  "root_cause": "The root cause is an unexpected surge in log file generation across multiple domains, leading to excessive disk usage.",
  "solution": "A comprehensive strategy was implemented: first, optimizing the log rotation settings; second, monitoring and limiting unnecessary background processes; third, enhancing storage management practices; and finally, educating the team on best practices for disk space management.",
  "ubuntu_value": "The Ubuntu collaboration improved the solution by ensuring a holistic approach that considered both immediate and long-term storage management needs. The collective insights allowed for a more robust and sustainable resolution.",
  "knowledge_articles": []
}